dzdsu/__init__.py
dzdsu/constants.py
dzdsu/hash.py
dzdsu/lockfile.py
dzdsu/mission.py
dzdsu/mods.py
dzdsu/params.py
dzdsu/parsers.py
dzdsu/rcon.py
dzdsu/server.py
dzdsu/update.py
dzdsu/wrapper.py
dzdsu/utility/__init__.py
dzdsu/utility/argparse.py
dzdsu/utility/backup.py
dzdsu/utility/logger.py
dzdsu/utility/mods.py
dzdsu/utility/shutdown.py
dzdsu/utility/update.py
dzdsu/utility/wipe.py
dzdsu-1.7.7.dist-info/LICENSE
dzdsu-1.7.7.dist-info/METADATA
dzdsu-1.7.7.dist-info/WHEEL
dzdsu-1.7.7.dist-info/entry_points.txt
dzdsu-1.7.7.dist-info/top_level.txt
dzdsu-1.7.7.dist-info/RECORD
