Metadata-Version: 2.1
Name: dzdsu
Version: 1.7.7
Summary: DayZ dedicated server utilities
Home-page: https://github.com/conqp/dzdsu
Author: Richard Neumann
Author-email: mail@richard-neumann.de
License: GPLv3
Keywords: DayZ dedicated server utilities
Platform: UNKNOWN
Requires-Python: >=3.10
License-File: LICENSE
Requires-Dist: psutil
Requires-Dist: rcon
